{
    "Object": {
        "Status": {
            "Type": {
                "id": 2,
                "enum": "Enemy"
            },
            "HP": 5,
            "Damage": 1,
            "Speed": 1.0,
            "isAlive": true
        },
        "Transform": {
            "position": {
                "x": 100.08010864257813,
                "y": -125.22465515136719
            },
            "scale": {
                "x": 50.0,
                "y": 50.0
            },
            "rotation": 0.0
        },
        "Sprite": {
            "is_flip": false,
            "image_path": "asset/images/Dr_Strange.png"
        },
        "Animation": {},
        "RigidBody": true,
        "Collision": {
            "id": 0,
            "enum": "box"
        },
        "Particle": {},
        "Sound": {},
        "Font": {}
    },
    "Object": {
        "Status": {},
        "Transform": {
            "position": {
                "x": 0.0,
                "y": 0.0
            },
            "scale": {
                "x": 1.0,
                "y": 1.0
            },
            "rotation": 0.0
        },
        "Sprite": {},
        "Animation": {},
        "RigidBody": false,
        "Collision": {},
        "Particle": {},
        "Sound": {},
        "Font": {}
    },
    "Object": {
        "Status": {
            "Type": {
                "id": 6,
                "enum": "Item"
            },
            "HP": 5,
            "Damage": 1,
            "Speed": 1.0,
            "isAlive": true
        },
        "Transform": {
            "position": {
                "x": 300.0,
                "y": 300.0
            },
            "scale": {
                "x": 24.0,
                "y": 30.0
            },
            "rotation": 0.0
        },
        "Sprite": {
            "is_flip": false,
            "image_path": "asset/images/red_soul.png"
        },
        "Animation": {},
        "RigidBody": false,
        "Collision": {
            "id": 0,
            "enum": "box"
        },
        "Particle": {},
        "Sound": {},
        "Font": {}
    },
    "Object": {
        "Status": {
            "Type": {
                "id": 6,
                "enum": "Item"
            },
            "HP": 5,
            "Damage": 1,
            "Speed": 1.0,
            "isAlive": true
        },
        "Transform": {
            "position": {
                "x": 250.0,
                "y": -250.0
            },
            "scale": {
                "x": 24.0,
                "y": 30.0
            },
            "rotation": 0.0
        },
        "Sprite": {
            "is_flip": false,
            "image_path": "asset/images/blue_soul.png"
        },
        "Animation": {},
        "RigidBody": false,
        "Collision": {
            "id": 0,
            "enum": "box"
        },
        "Particle": {},
        "Sound": {},
        "Font": {}
    },
    "Object": {
        "Status": {},
        "Transform": {
            "position": {
                "x": 50.0,
                "y": 0.0
            },
            "scale": {
                "x": 1.0,
                "y": 1.0
            },
            "rotation": 0.0
        },
        "Sprite": {},
        "Animation": {},
        "RigidBody": false,
        "Collision": {},
        "Particle": {},
        "Sound": {},
        "Font": {
            "text": "Hi Nice To Meet You",
            "path": "asset/font/hi.ttf"
        }
    },
    "Object": {
        "Status": {},
        "Transform": {
            "position": {
                "x": 0.0,
                "y": 0.0
            },
            "scale": {
                "x": 1280.0,
                "y": 960.0
            },
            "rotation": 0.0
        },
        "Sprite": {
            "is_flip": false,
            "image_path": "asset/images/background1.png"
        },
        "Animation": {},
        "RigidBody": false,
        "Collision": {},
        "Particle": {},
        "Sound": {},
        "Font": {}
    }
}