{
    "Tile": {
        "grid": 1664096,
        "tile_type": 1,
        "scale": {
            "x": 48.0,
            "y": 48.0
        },
        "pos": {
            "x": -136.0,
            "y": -488.0
        },
        "sprite": {
            "is_flip": false,
            "image_path": "asset/images/Tiles/Non_Ani/wall_left.png"
        },
        "animation": {},
        "IsAnimated": false,
        "collision": {}
    },
    "Tile": {
        "grid": 1536098,
        "tile_type": 1,
        "scale": {
            "x": 48.0,
            "y": 48.0
        },
        "pos": {
            "x": -616.0,
            "y": -392.0
        },
        "sprite": {
            "is_flip": false,
            "image_path": "asset/images/Tiles/Non_Ani/wall_left.png"
        },
        "animation": {},
        "IsAnimated": false,
        "collision": {}
    },
    "Tile": {
        "grid": 1843298,
        "tile_type": 1,
        "scale": {
            "x": 48.0,
            "y": 48.0
        },
        "pos": {
            "x": 536.0,
            "y": -392.0
        },
        "sprite": {
            "is_flip": false,
            "image_path": "asset/images/Tiles/Non_Ani/wall_left.png"
        },
        "animation": {},
        "IsAnimated": false,
        "collision": {}
    },
    "Tile": {
        "grid": 1536097,
        "tile_type": 1,
        "scale": {
            "x": 48.0,
            "y": 48.0
        },
        "pos": {
            "x": -616.0,
            "y": -440.0
        },
        "sprite": {
            "is_flip": false,
            "image_path": "asset/images/Tiles/Non_Ani/wall_left.png"
        },
        "animation": {},
        "IsAnimated": false,
        "collision": {}
    },
    "Tile": {
        "grid": 1753696,
        "tile_type": 1,
        "scale": {
            "x": 48.0,
            "y": 48.0
        },
        "pos": {
            "x": 200.0,
            "y": -488.0
        },
        "sprite": {
            "is_flip": false,
            "image_path": "asset/images/Tiles/Non_Ani/wall_left.png"
        },
        "animation": {},
        "IsAnimated": false,
        "collision": {}
    },
    "Tile": {
        "grid": 1638497,
        "tile_type": 1,
        "scale": {
            "x": 48.0,
            "y": 48.0
        },
        "pos": {
            "x": -232.0,
            "y": -440.0
        },
        "sprite": {
            "is_flip": false,
            "image_path": "asset/images/Tiles/Non_Ani/wall_left.png"
        },
        "animation": {},
        "IsAnimated": false,
        "collision": {}
    },
    "Tile": {
        "grid": 1587296,
        "tile_type": 1,
        "scale": {
            "x": 48.0,
            "y": 48.0
        },
        "pos": {
            "x": -424.0,
            "y": -488.0
        },
        "sprite": {
            "is_flip": false,
            "image_path": "asset/images/Tiles/Non_Ani/wall_left.png"
        },
        "animation": {},
        "IsAnimated": false,
        "collision": {}
    },
    "Tile": {
        "grid": 1548897,
        "tile_type": 1,
        "scale": {
            "x": 48.0,
            "y": 48.0
        },
        "pos": {
            "x": -568.0,
            "y": -440.0
        },
        "sprite": {
            "is_flip": false,
            "image_path": "asset/images/Tiles/Non_Ani/wall_left.png"
        },
        "animation": {},
        "IsAnimated": false,
        "collision": {}
    },
    "Tile": {
        "grid": 1676896,
        "tile_type": 1,
        "scale": {
            "x": 48.0,
            "y": 48.0
        },
        "pos": {
            "x": -88.0,
            "y": -488.0
        },
        "sprite": {
            "is_flip": false,
            "image_path": "asset/images/Tiles/Non_Ani/wall_left.png"
        },
        "animation": {},
        "IsAnimated": false,
        "collision": {}
    },
    "Tile": {
        "grid": 1766497,
        "tile_type": 1,
        "scale": {
            "x": 48.0,
            "y": 48.0
        },
        "pos": {
            "x": 248.0,
            "y": -440.0
        },
        "sprite": {
            "is_flip": false,
            "image_path": "asset/images/Tiles/Non_Ani/wall_left.png"
        },
        "animation": {},
        "IsAnimated": false,
        "collision": {}
    },
    "Tile": {
        "grid": 1548898,
        "tile_type": 1,
        "scale": {
            "x": 48.0,
            "y": 48.0
        },
        "pos": {
            "x": -568.0,
            "y": -392.0
        },
        "sprite": {
            "is_flip": false,
            "image_path": "asset/images/Tiles/Non_Ani/wall_left.png"
        },
        "animation": {},
        "IsAnimated": false,
        "collision": {}
    },
    "Tile": {
        "grid": 1561698,
        "tile_type": 1,
        "scale": {
            "x": 48.0,
            "y": 48.0
        },
        "pos": {
            "x": -520.0,
            "y": -392.0
        },
        "sprite": {
            "is_flip": false,
            "image_path": "asset/images/Tiles/Non_Ani/wall_left.png"
        },
        "animation": {},
        "IsAnimated": false,
        "collision": {}
    },
    "Tile": {
        "grid": 1638496,
        "tile_type": 1,
        "scale": {
            "x": 48.0,
            "y": 48.0
        },
        "pos": {
            "x": -232.0,
            "y": -488.0
        },
        "sprite": {
            "is_flip": false,
            "image_path": "asset/images/Tiles/Non_Ani/wall_left.png"
        },
        "animation": {},
        "IsAnimated": false,
        "collision": {}
    },
    "Tile": {
        "grid": 1753698,
        "tile_type": 1,
        "scale": {
            "x": 48.0,
            "y": 48.0
        },
        "pos": {
            "x": 200.0,
            "y": -392.0
        },
        "sprite": {
            "is_flip": false,
            "image_path": "asset/images/Tiles/Non_Ani/wall_left.png"
        },
        "animation": {},
        "IsAnimated": false,
        "collision": {}
    },
    "Tile": {
        "grid": 1561697,
        "tile_type": 1,
        "scale": {
            "x": 48.0,
            "y": 48.0
        },
        "pos": {
            "x": -520.0,
            "y": -440.0
        },
        "sprite": {
            "is_flip": false,
            "image_path": "asset/images/Tiles/Non_Ani/wall_left.png"
        },
        "animation": {},
        "IsAnimated": false,
        "collision": {}
    },
    "Tile": {
        "grid": 1587298,
        "tile_type": 1,
        "scale": {
            "x": 48.0,
            "y": 48.0
        },
        "pos": {
            "x": -424.0,
            "y": -392.0
        },
        "sprite": {
            "is_flip": false,
            "image_path": "asset/images/Tiles/Non_Ani/wall_left.png"
        },
        "animation": {},
        "IsAnimated": false,
        "collision": {}
    },
    "Tile": {
        "grid": 1856097,
        "tile_type": 1,
        "scale": {
            "x": 48.0,
            "y": 48.0
        },
        "pos": {
            "x": 584.0,
            "y": -440.0
        },
        "sprite": {
            "is_flip": false,
            "image_path": "asset/images/Tiles/Non_Ani/wall_left.png"
        },
        "animation": {},
        "IsAnimated": false,
        "collision": {}
    },
    "Tile": {
        "grid": 1574497,
        "tile_type": 1,
        "scale": {
            "x": 48.0,
            "y": 48.0
        },
        "pos": {
            "x": -472.0,
            "y": -440.0
        },
        "sprite": {
            "is_flip": false,
            "image_path": "asset/images/Tiles/Non_Ani/wall_left.png"
        },
        "animation": {},
        "IsAnimated": false,
        "collision": {}
    },
    "Tile": {
        "grid": 1612896,
        "tile_type": 1,
        "scale": {
            "x": 48.0,
            "y": 48.0
        },
        "pos": {
            "x": -328.0,
            "y": -488.0
        },
        "sprite": {
            "is_flip": false,
            "image_path": "asset/images/Tiles/Non_Ani/wall_left.png"
        },
        "animation": {},
        "IsAnimated": false,
        "collision": {}
    },
    "Tile": {
        "grid": 1664097,
        "tile_type": 1,
        "scale": {
            "x": 48.0,
            "y": 48.0
        },
        "pos": {
            "x": -136.0,
            "y": -440.0
        },
        "sprite": {
            "is_flip": false,
            "image_path": "asset/images/Tiles/Non_Ani/wall_left.png"
        },
        "animation": {},
        "IsAnimated": false,
        "collision": {}
    },
    "Tile": {
        "grid": 1574498,
        "tile_type": 1,
        "scale": {
            "x": 48.0,
            "y": 48.0
        },
        "pos": {
            "x": -472.0,
            "y": -392.0
        },
        "sprite": {
            "is_flip": false,
            "image_path": "asset/images/Tiles/Non_Ani/wall_left.png"
        },
        "animation": {},
        "IsAnimated": false,
        "collision": {}
    },
    "Tile": {
        "grid": 1600098,
        "tile_type": 1,
        "scale": {
            "x": 48.0,
            "y": 48.0
        },
        "pos": {
            "x": -376.0,
            "y": -392.0
        },
        "sprite": {
            "is_flip": false,
            "image_path": "asset/images/Tiles/Non_Ani/wall_left.png"
        },
        "animation": {},
        "IsAnimated": false,
        "collision": {}
    },
    "Tile": {
        "grid": 1651297,
        "tile_type": 1,
        "scale": {
            "x": 48.0,
            "y": 48.0
        },
        "pos": {
            "x": -184.0,
            "y": -440.0
        },
        "sprite": {
            "is_flip": false,
            "image_path": "asset/images/Tiles/Non_Ani/wall_left.png"
        },
        "animation": {},
        "IsAnimated": false,
        "collision": {}
    },
    "Tile": {
        "grid": 1574496,
        "tile_type": 1,
        "scale": {
            "x": 48.0,
            "y": 48.0
        },
        "pos": {
            "x": -472.0,
            "y": -488.0
        },
        "sprite": {
            "is_flip": false,
            "image_path": "asset/images/Tiles/Non_Ani/wall_left.png"
        },
        "animation": {},
        "IsAnimated": false,
        "collision": {}
    },
    "Tile": {
        "grid": 1612898,
        "tile_type": 1,
        "scale": {
            "x": 48.0,
            "y": 48.0
        },
        "pos": {
            "x": -328.0,
            "y": -392.0
        },
        "sprite": {
            "is_flip": false,
            "image_path": "asset/images/Tiles/Non_Ani/wall_left.png"
        },
        "animation": {},
        "IsAnimated": false,
        "collision": {}
    },
    "Tile": {
        "grid": 1728096,
        "tile_type": 1,
        "scale": {
            "x": 48.0,
            "y": 48.0
        },
        "pos": {
            "x": 104.0,
            "y": -488.0
        },
        "sprite": {
            "is_flip": false,
            "image_path": "asset/images/Tiles/Non_Ani/wall_left.png"
        },
        "animation": {},
        "IsAnimated": false,
        "collision": {}
    },
    "Tile": {
        "grid": 1625698,
        "tile_type": 1,
        "scale": {
            "x": 48.0,
            "y": 48.0
        },
        "pos": {
            "x": -280.0,
            "y": -392.0
        },
        "sprite": {
            "is_flip": false,
            "image_path": "asset/images/Tiles/Non_Ani/wall_left.png"
        },
        "animation": {},
        "IsAnimated": false,
        "collision": {}
    },
    "Tile": {
        "grid": 1638498,
        "tile_type": 1,
        "scale": {
            "x": 48.0,
            "y": 48.0
        },
        "pos": {
            "x": -232.0,
            "y": -392.0
        },
        "sprite": {
            "is_flip": false,
            "image_path": "asset/images/Tiles/Non_Ani/wall_left.png"
        },
        "animation": {},
        "IsAnimated": false,
        "collision": {}
    },
    "Tile": {
        "grid": 1561696,
        "tile_type": 1,
        "scale": {
            "x": 48.0,
            "y": 48.0
        },
        "pos": {
            "x": -520.0,
            "y": -488.0
        },
        "sprite": {
            "is_flip": false,
            "image_path": "asset/images/Tiles/Non_Ani/wall_left.png"
        },
        "animation": {},
        "IsAnimated": false,
        "collision": {}
    },
    "Tile": {
        "grid": 1804898,
        "tile_type": 1,
        "scale": {
            "x": 48.0,
            "y": 48.0
        },
        "pos": {
            "x": 392.0,
            "y": -392.0
        },
        "sprite": {
            "is_flip": false,
            "image_path": "asset/images/Tiles/Non_Ani/wall_left.png"
        },
        "animation": {},
        "IsAnimated": false,
        "collision": {}
    },
    "Tile": {
        "grid": 1728097,
        "tile_type": 1,
        "scale": {
            "x": 48.0,
            "y": 48.0
        },
        "pos": {
            "x": 104.0,
            "y": -440.0
        },
        "sprite": {
            "is_flip": false,
            "image_path": "asset/images/Tiles/Non_Ani/wall_left.png"
        },
        "animation": {},
        "IsAnimated": false,
        "collision": {}
    },
    "Tile": {
        "grid": 1651298,
        "tile_type": 1,
        "scale": {
            "x": 48.0,
            "y": 48.0
        },
        "pos": {
            "x": -184.0,
            "y": -392.0
        },
        "sprite": {
            "is_flip": false,
            "image_path": "asset/images/Tiles/Non_Ani/wall_left.png"
        },
        "animation": {},
        "IsAnimated": false,
        "collision": {}
    },
    "Tile": {
        "grid": 1536096,
        "tile_type": 1,
        "scale": {
            "x": 48.0,
            "y": 48.0
        },
        "pos": {
            "x": -616.0,
            "y": -488.0
        },
        "sprite": {
            "is_flip": false,
            "image_path": "asset/images/Tiles/Non_Ani/wall_left.png"
        },
        "animation": {},
        "IsAnimated": false,
        "collision": {}
    },
    "Tile": {
        "grid": 1830498,
        "tile_type": 1,
        "scale": {
            "x": 48.0,
            "y": 48.0
        },
        "pos": {
            "x": 488.0,
            "y": -392.0
        },
        "sprite": {
            "is_flip": false,
            "image_path": "asset/images/Tiles/Non_Ani/wall_left.png"
        },
        "animation": {},
        "IsAnimated": false,
        "collision": {}
    },
    "Tile": {
        "grid": 1664098,
        "tile_type": 1,
        "scale": {
            "x": 48.0,
            "y": 48.0
        },
        "pos": {
            "x": -136.0,
            "y": -392.0
        },
        "sprite": {
            "is_flip": false,
            "image_path": "asset/images/Tiles/Non_Ani/wall_left.png"
        },
        "animation": {},
        "IsAnimated": false,
        "collision": {}
    },
    "Tile": {
        "grid": 1676898,
        "tile_type": 1,
        "scale": {
            "x": 48.0,
            "y": 48.0
        },
        "pos": {
            "x": -88.0,
            "y": -392.0
        },
        "sprite": {
            "is_flip": false,
            "image_path": "asset/images/Tiles/Non_Ani/wall_left.png"
        },
        "animation": {},
        "IsAnimated": false,
        "collision": {}
    },
    "Tile": {
        "grid": 1689698,
        "tile_type": 1,
        "scale": {
            "x": 48.0,
            "y": 48.0
        },
        "pos": {
            "x": -40.0,
            "y": -392.0
        },
        "sprite": {
            "is_flip": false,
            "image_path": "asset/images/Tiles/Non_Ani/wall_left.png"
        },
        "animation": {},
        "IsAnimated": false,
        "collision": {}
    },
    "Tile": {
        "grid": 1702498,
        "tile_type": 1,
        "scale": {
            "x": 48.0,
            "y": 48.0
        },
        "pos": {
            "x": 8.0,
            "y": -392.0
        },
        "sprite": {
            "is_flip": false,
            "image_path": "asset/images/Tiles/Non_Ani/wall_left.png"
        },
        "animation": {},
        "IsAnimated": false,
        "collision": {}
    },
    "Tile": {
        "grid": 1715298,
        "tile_type": 1,
        "scale": {
            "x": 48.0,
            "y": 48.0
        },
        "pos": {
            "x": 56.0,
            "y": -392.0
        },
        "sprite": {
            "is_flip": false,
            "image_path": "asset/images/Tiles/Non_Ani/wall_left.png"
        },
        "animation": {},
        "IsAnimated": false,
        "collision": {}
    },
    "Tile": {
        "grid": 1728098,
        "tile_type": 1,
        "scale": {
            "x": 48.0,
            "y": 48.0
        },
        "pos": {
            "x": 104.0,
            "y": -392.0
        },
        "sprite": {
            "is_flip": false,
            "image_path": "asset/images/Tiles/Non_Ani/wall_left.png"
        },
        "animation": {},
        "IsAnimated": false,
        "collision": {}
    },
    "Tile": {
        "grid": 1625696,
        "tile_type": 1,
        "scale": {
            "x": 48.0,
            "y": 48.0
        },
        "pos": {
            "x": -280.0,
            "y": -488.0
        },
        "sprite": {
            "is_flip": false,
            "image_path": "asset/images/Tiles/Non_Ani/wall_left.png"
        },
        "animation": {},
        "IsAnimated": false,
        "collision": {}
    },
    "Tile": {
        "grid": 1702497,
        "tile_type": 1,
        "scale": {
            "x": 48.0,
            "y": 48.0
        },
        "pos": {
            "x": 8.0,
            "y": -440.0
        },
        "sprite": {
            "is_flip": false,
            "image_path": "asset/images/Tiles/Non_Ani/wall_left.png"
        },
        "animation": {},
        "IsAnimated": false,
        "collision": {}
    },
    "Tile": {
        "grid": 1689697,
        "tile_type": 1,
        "scale": {
            "x": 48.0,
            "y": 48.0
        },
        "pos": {
            "x": -40.0,
            "y": -440.0
        },
        "sprite": {
            "is_flip": false,
            "image_path": "asset/images/Tiles/Non_Ani/wall_left.png"
        },
        "animation": {},
        "IsAnimated": false,
        "collision": {}
    },
    "Tile": {
        "grid": 1740898,
        "tile_type": 1,
        "scale": {
            "x": 48.0,
            "y": 48.0
        },
        "pos": {
            "x": 152.0,
            "y": -392.0
        },
        "sprite": {
            "is_flip": false,
            "image_path": "asset/images/Tiles/Non_Ani/wall_left.png"
        },
        "animation": {},
        "IsAnimated": false,
        "collision": {}
    },
    "Tile": {
        "grid": 1766498,
        "tile_type": 1,
        "scale": {
            "x": 48.0,
            "y": 48.0
        },
        "pos": {
            "x": 248.0,
            "y": -392.0
        },
        "sprite": {
            "is_flip": false,
            "image_path": "asset/images/Tiles/Non_Ani/wall_left.png"
        },
        "animation": {},
        "IsAnimated": false,
        "collision": {}
    },
    "Tile": {
        "grid": 1779298,
        "tile_type": 1,
        "scale": {
            "x": 48.0,
            "y": 48.0
        },
        "pos": {
            "x": 296.0,
            "y": -392.0
        },
        "sprite": {
            "is_flip": false,
            "image_path": "asset/images/Tiles/Non_Ani/wall_left.png"
        },
        "animation": {},
        "IsAnimated": false,
        "collision": {}
    },
    "Tile": {
        "grid": 1792098,
        "tile_type": 1,
        "scale": {
            "x": 48.0,
            "y": 48.0
        },
        "pos": {
            "x": 344.0,
            "y": -392.0
        },
        "sprite": {
            "is_flip": false,
            "image_path": "asset/images/Tiles/Non_Ani/wall_left.png"
        },
        "animation": {},
        "IsAnimated": false,
        "collision": {}
    },
    "Tile": {
        "grid": 1817698,
        "tile_type": 1,
        "scale": {
            "x": 48.0,
            "y": 48.0
        },
        "pos": {
            "x": 440.0,
            "y": -392.0
        },
        "sprite": {
            "is_flip": false,
            "image_path": "asset/images/Tiles/Non_Ani/wall_left.png"
        },
        "animation": {},
        "IsAnimated": false,
        "collision": {}
    },
    "Tile": {
        "grid": 1804897,
        "tile_type": 1,
        "scale": {
            "x": 48.0,
            "y": 48.0
        },
        "pos": {
            "x": 392.0,
            "y": -440.0
        },
        "sprite": {
            "is_flip": false,
            "image_path": "asset/images/Tiles/Non_Ani/wall_left.png"
        },
        "animation": {},
        "IsAnimated": false,
        "collision": {}
    },
    "Tile": {
        "grid": 1856098,
        "tile_type": 1,
        "scale": {
            "x": 48.0,
            "y": 48.0
        },
        "pos": {
            "x": 584.0,
            "y": -392.0
        },
        "sprite": {
            "is_flip": false,
            "image_path": "asset/images/Tiles/Non_Ani/wall_left.png"
        },
        "animation": {},
        "IsAnimated": false,
        "collision": {}
    },
    "Tile": {
        "grid": 1868898,
        "tile_type": 1,
        "scale": {
            "x": 48.0,
            "y": 48.0
        },
        "pos": {
            "x": 632.0,
            "y": -392.0
        },
        "sprite": {
            "is_flip": false,
            "image_path": "asset/images/Tiles/Non_Ani/wall_left.png"
        },
        "animation": {},
        "IsAnimated": false,
        "collision": {}
    },
    "Tile": {
        "grid": 1843297,
        "tile_type": 1,
        "scale": {
            "x": 48.0,
            "y": 48.0
        },
        "pos": {
            "x": 536.0,
            "y": -440.0
        },
        "sprite": {
            "is_flip": false,
            "image_path": "asset/images/Tiles/Non_Ani/wall_left.png"
        },
        "animation": {},
        "IsAnimated": false,
        "collision": {}
    },
    "Tile": {
        "grid": 1830497,
        "tile_type": 1,
        "scale": {
            "x": 48.0,
            "y": 48.0
        },
        "pos": {
            "x": 488.0,
            "y": -440.0
        },
        "sprite": {
            "is_flip": false,
            "image_path": "asset/images/Tiles/Non_Ani/wall_left.png"
        },
        "animation": {},
        "IsAnimated": false,
        "collision": {}
    },
    "Tile": {
        "grid": 1817697,
        "tile_type": 1,
        "scale": {
            "x": 48.0,
            "y": 48.0
        },
        "pos": {
            "x": 440.0,
            "y": -440.0
        },
        "sprite": {
            "is_flip": false,
            "image_path": "asset/images/Tiles/Non_Ani/wall_left.png"
        },
        "animation": {},
        "IsAnimated": false,
        "collision": {}
    },
    "Tile": {
        "grid": 1792097,
        "tile_type": 1,
        "scale": {
            "x": 48.0,
            "y": 48.0
        },
        "pos": {
            "x": 344.0,
            "y": -440.0
        },
        "sprite": {
            "is_flip": false,
            "image_path": "asset/images/Tiles/Non_Ani/wall_left.png"
        },
        "animation": {},
        "IsAnimated": false,
        "collision": {}
    },
    "Tile": {
        "grid": 1779297,
        "tile_type": 1,
        "scale": {
            "x": 48.0,
            "y": 48.0
        },
        "pos": {
            "x": 296.0,
            "y": -440.0
        },
        "sprite": {
            "is_flip": false,
            "image_path": "asset/images/Tiles/Non_Ani/wall_left.png"
        },
        "animation": {},
        "IsAnimated": false,
        "collision": {}
    },
    "Tile": {
        "grid": 1548896,
        "tile_type": 1,
        "scale": {
            "x": 48.0,
            "y": 48.0
        },
        "pos": {
            "x": -568.0,
            "y": -488.0
        },
        "sprite": {
            "is_flip": false,
            "image_path": "asset/images/Tiles/Non_Ani/wall_left.png"
        },
        "animation": {},
        "IsAnimated": false,
        "collision": {}
    },
    "Tile": {
        "grid": 1753697,
        "tile_type": 1,
        "scale": {
            "x": 48.0,
            "y": 48.0
        },
        "pos": {
            "x": 200.0,
            "y": -440.0
        },
        "sprite": {
            "is_flip": false,
            "image_path": "asset/images/Tiles/Non_Ani/wall_left.png"
        },
        "animation": {},
        "IsAnimated": false,
        "collision": {}
    },
    "Tile": {
        "grid": 1651296,
        "tile_type": 1,
        "scale": {
            "x": 48.0,
            "y": 48.0
        },
        "pos": {
            "x": -184.0,
            "y": -488.0
        },
        "sprite": {
            "is_flip": false,
            "image_path": "asset/images/Tiles/Non_Ani/wall_left.png"
        },
        "animation": {},
        "IsAnimated": false,
        "collision": {}
    },
    "Tile": {
        "grid": 1740897,
        "tile_type": 1,
        "scale": {
            "x": 48.0,
            "y": 48.0
        },
        "pos": {
            "x": 152.0,
            "y": -440.0
        },
        "sprite": {
            "is_flip": false,
            "image_path": "asset/images/Tiles/Non_Ani/wall_left.png"
        },
        "animation": {},
        "IsAnimated": false,
        "collision": {}
    },
    "Tile": {
        "grid": 1715297,
        "tile_type": 1,
        "scale": {
            "x": 48.0,
            "y": 48.0
        },
        "pos": {
            "x": 56.0,
            "y": -440.0
        },
        "sprite": {
            "is_flip": false,
            "image_path": "asset/images/Tiles/Non_Ani/wall_left.png"
        },
        "animation": {},
        "IsAnimated": false,
        "collision": {}
    },
    "Tile": {
        "grid": 1600096,
        "tile_type": 1,
        "scale": {
            "x": 48.0,
            "y": 48.0
        },
        "pos": {
            "x": -376.0,
            "y": -488.0
        },
        "sprite": {
            "is_flip": false,
            "image_path": "asset/images/Tiles/Non_Ani/wall_left.png"
        },
        "animation": {},
        "IsAnimated": false,
        "collision": {}
    },
    "Tile": {
        "grid": 1676897,
        "tile_type": 1,
        "scale": {
            "x": 48.0,
            "y": 48.0
        },
        "pos": {
            "x": -88.0,
            "y": -440.0
        },
        "sprite": {
            "is_flip": false,
            "image_path": "asset/images/Tiles/Non_Ani/wall_left.png"
        },
        "animation": {},
        "IsAnimated": false,
        "collision": {}
    },
    "Tile": {
        "grid": 1625697,
        "tile_type": 1,
        "scale": {
            "x": 48.0,
            "y": 48.0
        },
        "pos": {
            "x": -280.0,
            "y": -440.0
        },
        "sprite": {
            "is_flip": false,
            "image_path": "asset/images/Tiles/Non_Ani/wall_left.png"
        },
        "animation": {},
        "IsAnimated": false,
        "collision": {}
    },
    "Tile": {
        "grid": 1612897,
        "tile_type": 1,
        "scale": {
            "x": 48.0,
            "y": 48.0
        },
        "pos": {
            "x": -328.0,
            "y": -440.0
        },
        "sprite": {
            "is_flip": false,
            "image_path": "asset/images/Tiles/Non_Ani/wall_left.png"
        },
        "animation": {},
        "IsAnimated": false,
        "collision": {}
    },
    "Tile": {
        "grid": 1587297,
        "tile_type": 1,
        "scale": {
            "x": 48.0,
            "y": 48.0
        },
        "pos": {
            "x": -424.0,
            "y": -440.0
        },
        "sprite": {
            "is_flip": false,
            "image_path": "asset/images/Tiles/Non_Ani/wall_left.png"
        },
        "animation": {},
        "IsAnimated": false,
        "collision": {}
    },
    "Tile": {
        "grid": 1600097,
        "tile_type": 1,
        "scale": {
            "x": 48.0,
            "y": 48.0
        },
        "pos": {
            "x": -376.0,
            "y": -440.0
        },
        "sprite": {
            "is_flip": false,
            "image_path": "asset/images/Tiles/Non_Ani/wall_left.png"
        },
        "animation": {},
        "IsAnimated": false,
        "collision": {}
    },
    "Tile": {
        "grid": 1689696,
        "tile_type": 1,
        "scale": {
            "x": 48.0,
            "y": 48.0
        },
        "pos": {
            "x": -40.0,
            "y": -488.0
        },
        "sprite": {
            "is_flip": false,
            "image_path": "asset/images/Tiles/Non_Ani/wall_left.png"
        },
        "animation": {},
        "IsAnimated": false,
        "collision": {}
    },
    "Tile": {
        "grid": 1702496,
        "tile_type": 1,
        "scale": {
            "x": 48.0,
            "y": 48.0
        },
        "pos": {
            "x": 8.0,
            "y": -488.0
        },
        "sprite": {
            "is_flip": false,
            "image_path": "asset/images/Tiles/Non_Ani/wall_left.png"
        },
        "animation": {},
        "IsAnimated": false,
        "collision": {}
    },
    "Tile": {
        "grid": 1715296,
        "tile_type": 1,
        "scale": {
            "x": 48.0,
            "y": 48.0
        },
        "pos": {
            "x": 56.0,
            "y": -488.0
        },
        "sprite": {
            "is_flip": false,
            "image_path": "asset/images/Tiles/Non_Ani/wall_left.png"
        },
        "animation": {},
        "IsAnimated": false,
        "collision": {}
    },
    "Tile": {
        "grid": 1740896,
        "tile_type": 1,
        "scale": {
            "x": 48.0,
            "y": 48.0
        },
        "pos": {
            "x": 152.0,
            "y": -488.0
        },
        "sprite": {
            "is_flip": false,
            "image_path": "asset/images/Tiles/Non_Ani/wall_left.png"
        },
        "animation": {},
        "IsAnimated": false,
        "collision": {}
    },
    "Tile": {
        "grid": 1766496,
        "tile_type": 1,
        "scale": {
            "x": 48.0,
            "y": 48.0
        },
        "pos": {
            "x": 248.0,
            "y": -488.0
        },
        "sprite": {
            "is_flip": false,
            "image_path": "asset/images/Tiles/Non_Ani/wall_left.png"
        },
        "animation": {},
        "IsAnimated": false,
        "collision": {}
    },
    "Tile": {
        "grid": 1779296,
        "tile_type": 1,
        "scale": {
            "x": 48.0,
            "y": 48.0
        },
        "pos": {
            "x": 296.0,
            "y": -488.0
        },
        "sprite": {
            "is_flip": false,
            "image_path": "asset/images/Tiles/Non_Ani/wall_left.png"
        },
        "animation": {},
        "IsAnimated": false,
        "collision": {}
    },
    "Tile": {
        "grid": 1792096,
        "tile_type": 1,
        "scale": {
            "x": 48.0,
            "y": 48.0
        },
        "pos": {
            "x": 344.0,
            "y": -488.0
        },
        "sprite": {
            "is_flip": false,
            "image_path": "asset/images/Tiles/Non_Ani/wall_left.png"
        },
        "animation": {},
        "IsAnimated": false,
        "collision": {}
    },
    "Tile": {
        "grid": 1804896,
        "tile_type": 1,
        "scale": {
            "x": 48.0,
            "y": 48.0
        },
        "pos": {
            "x": 392.0,
            "y": -488.0
        },
        "sprite": {
            "is_flip": false,
            "image_path": "asset/images/Tiles/Non_Ani/wall_left.png"
        },
        "animation": {},
        "IsAnimated": false,
        "collision": {}
    },
    "Tile": {
        "grid": 1817696,
        "tile_type": 1,
        "scale": {
            "x": 48.0,
            "y": 48.0
        },
        "pos": {
            "x": 440.0,
            "y": -488.0
        },
        "sprite": {
            "is_flip": false,
            "image_path": "asset/images/Tiles/Non_Ani/wall_left.png"
        },
        "animation": {},
        "IsAnimated": false,
        "collision": {}
    },
    "Tile": {
        "grid": 1830496,
        "tile_type": 1,
        "scale": {
            "x": 48.0,
            "y": 48.0
        },
        "pos": {
            "x": 488.0,
            "y": -488.0
        },
        "sprite": {
            "is_flip": false,
            "image_path": "asset/images/Tiles/Non_Ani/wall_left.png"
        },
        "animation": {},
        "IsAnimated": false,
        "collision": {}
    },
    "Tile": {
        "grid": 1843296,
        "tile_type": 1,
        "scale": {
            "x": 48.0,
            "y": 48.0
        },
        "pos": {
            "x": 536.0,
            "y": -488.0
        },
        "sprite": {
            "is_flip": false,
            "image_path": "asset/images/Tiles/Non_Ani/wall_left.png"
        },
        "animation": {},
        "IsAnimated": false,
        "collision": {}
    },
    "Tile": {
        "grid": 1856096,
        "tile_type": 1,
        "scale": {
            "x": 48.0,
            "y": 48.0
        },
        "pos": {
            "x": 584.0,
            "y": -488.0
        },
        "sprite": {
            "is_flip": false,
            "image_path": "asset/images/Tiles/Non_Ani/wall_left.png"
        },
        "animation": {},
        "IsAnimated": false,
        "collision": {}
    },
    "Tile": {
        "grid": 1868896,
        "tile_type": 1,
        "scale": {
            "x": 48.0,
            "y": 48.0
        },
        "pos": {
            "x": 632.0,
            "y": -488.0
        },
        "sprite": {
            "is_flip": false,
            "image_path": "asset/images/Tiles/Non_Ani/wall_left.png"
        },
        "animation": {},
        "IsAnimated": false,
        "collision": {}
    },
    "Tile": {
        "grid": 1868897,
        "tile_type": 1,
        "scale": {
            "x": 48.0,
            "y": 48.0
        },
        "pos": {
            "x": 632.0,
            "y": -440.0
        },
        "sprite": {
            "is_flip": false,
            "image_path": "asset/images/Tiles/Non_Ani/wall_left.png"
        },
        "animation": {},
        "IsAnimated": false,
        "collision": {}
    },
    "Tile": {
        "grid": 1792112,
        "tile_type": 1,
        "scale": {
            "x": 48.0,
            "y": 48.0
        },
        "pos": {
            "x": 344.0,
            "y": 280.0
        },
        "sprite": {
            "is_flip": false,
            "image_path": "asset/images/Tiles/Non_Ani/wall_right.png"
        },
        "animation": {},
        "IsAnimated": false,
        "collision": {}
    },
    "Tile": {
        "grid": 1804912,
        "tile_type": 1,
        "scale": {
            "x": 48.0,
            "y": 48.0
        },
        "pos": {
            "x": 392.0,
            "y": 280.0
        },
        "sprite": {
            "is_flip": false,
            "image_path": "asset/images/Tiles/Non_Ani/wall_right.png"
        },
        "animation": {},
        "IsAnimated": false,
        "collision": {}
    },
    "Tile": {
        "grid": 1817712,
        "tile_type": 1,
        "scale": {
            "x": 48.0,
            "y": 48.0
        },
        "pos": {
            "x": 440.0,
            "y": 280.0
        },
        "sprite": {
            "is_flip": false,
            "image_path": "asset/images/Tiles/Non_Ani/wall_right.png"
        },
        "animation": {},
        "IsAnimated": false,
        "collision": {}
    },
    "Tile": {
        "grid": 1830512,
        "tile_type": 1,
        "scale": {
            "x": 48.0,
            "y": 48.0
        },
        "pos": {
            "x": 488.0,
            "y": 280.0
        },
        "sprite": {
            "is_flip": false,
            "image_path": "asset/images/Tiles/Non_Ani/wall_right.png"
        },
        "animation": {},
        "IsAnimated": false,
        "collision": {}
    },
    "Tile": {
        "grid": 1843312,
        "tile_type": 1,
        "scale": {
            "x": 48.0,
            "y": 48.0
        },
        "pos": {
            "x": 536.0,
            "y": 280.0
        },
        "sprite": {
            "is_flip": false,
            "image_path": "asset/images/Tiles/Non_Ani/wall_right.png"
        },
        "animation": {},
        "IsAnimated": false,
        "collision": {}
    },
    "Tile": {
        "grid": 1856112,
        "tile_type": 1,
        "scale": {
            "x": 48.0,
            "y": 48.0
        },
        "pos": {
            "x": 584.0,
            "y": 280.0
        },
        "sprite": {
            "is_flip": false,
            "image_path": "asset/images/Tiles/Non_Ani/wall_right.png"
        },
        "animation": {},
        "IsAnimated": false,
        "collision": {}
    },
    "Tile": {
        "grid": 1868912,
        "tile_type": 1,
        "scale": {
            "x": 48.0,
            "y": 48.0
        },
        "pos": {
            "x": 632.0,
            "y": 280.0
        },
        "sprite": {
            "is_flip": false,
            "image_path": "asset/images/Tiles/Non_Ani/wall_right.png"
        },
        "animation": {},
        "IsAnimated": false,
        "collision": {}
    }
}