{
    "Tile": {
        "grid": 652861,
        "tile_type": 0,
        "scale": {
            "x": 96.0,
            "y": 96.0
        },
        "pos": {
            "x": -1456.0,
            "y": 784.0
        },
        "sprite": {
            "is_flip": false,
            "image_path": "asset/images/Tiles/Non_Ani/Tile_DR_C.png"
        },
        "animation": {},
        "IsAnimated": false,
        "collision": {
            "id": 0,
            "enum": "box"
        }
    },
    "Tile": {
        "grid": 665661,
        "tile_type": 0,
        "scale": {
            "x": 96.0,
            "y": 96.0
        },
        "pos": {
            "x": -1360.0,
            "y": 784.0
        },
        "sprite": {
            "is_flip": false,
            "image_path": "asset/images/Tiles/Non_Ani/Tile_D.png"
        },
        "animation": {},
        "IsAnimated": false,
        "collision": {
            "id": 0,
            "enum": "box"
        }
    },
    "Tile": {
        "grid": 806457,
        "tile_type": 0,
        "scale": {
            "x": 96.0,
            "y": 96.0
        },
        "pos": {
            "x": -304.0,
            "y": 400.0
        },
        "sprite": {
            "is_flip": false,
            "image_path": "asset/images/Tiles/Non_Ani/Tile_T.png"
        },
        "animation": {},
        "IsAnimated": false,
        "collision": {
            "id": 0,
            "enum": "box"
        }
    },
    "Tile": {
        "grid": 716861,
        "tile_type": 0,
        "scale": {
            "x": 96.0,
            "y": 96.0
        },
        "pos": {
            "x": -976.0,
            "y": 784.0
        },
        "sprite": {
            "is_flip": false,
            "image_path": "asset/images/Tiles/Non_Ani/Tile_D.png"
        },
        "animation": {},
        "IsAnimated": false,
        "collision": {
            "id": 0,
            "enum": "box"
        }
    },
    "Tile": {
        "grid": 678461,
        "tile_type": 0,
        "scale": {
            "x": 96.0,
            "y": 96.0
        },
        "pos": {
            "x": -1264.0,
            "y": 784.0
        },
        "sprite": {
            "is_flip": false,
            "image_path": "asset/images/Tiles/Non_Ani/Tile_D.png"
        },
        "animation": {},
        "IsAnimated": false,
        "collision": {
            "id": 0,
            "enum": "box"
        }
    },
    "Tile": {
        "grid": 691261,
        "tile_type": 0,
        "scale": {
            "x": 96.0,
            "y": 96.0
        },
        "pos": {
            "x": -1168.0,
            "y": 784.0
        },
        "sprite": {
            "is_flip": false,
            "image_path": "asset/images/Tiles/Non_Ani/Tile_D.png"
        },
        "animation": {},
        "IsAnimated": false,
        "collision": {
            "id": 0,
            "enum": "box"
        }
    },
    "Tile": {
        "grid": 704061,
        "tile_type": 0,
        "scale": {
            "x": 96.0,
            "y": 96.0
        },
        "pos": {
            "x": -1072.0,
            "y": 784.0
        },
        "sprite": {
            "is_flip": false,
            "image_path": "asset/images/Tiles/Non_Ani/Tile_D.png"
        },
        "animation": {},
        "IsAnimated": false,
        "collision": {
            "id": 0,
            "enum": "box"
        }
    },
    "Tile": {
        "grid": 729661,
        "tile_type": 0,
        "scale": {
            "x": 96.0,
            "y": 96.0
        },
        "pos": {
            "x": -880.0,
            "y": 784.0
        },
        "sprite": {
            "is_flip": false,
            "image_path": "asset/images/Tiles/Non_Ani/Tile_D.png"
        },
        "animation": {},
        "IsAnimated": false,
        "collision": {
            "id": 0,
            "enum": "box"
        }
    },
    "Tile": {
        "grid": 742461,
        "tile_type": 0,
        "scale": {
            "x": 96.0,
            "y": 96.0
        },
        "pos": {
            "x": -784.0,
            "y": 784.0
        },
        "sprite": {
            "is_flip": false,
            "image_path": "asset/images/Tiles/Non_Ani/Tile_D.png"
        },
        "animation": {},
        "IsAnimated": false,
        "collision": {
            "id": 0,
            "enum": "box"
        }
    },
    "Tile": {
        "grid": 755261,
        "tile_type": 0,
        "scale": {
            "x": 96.0,
            "y": 96.0
        },
        "pos": {
            "x": -688.0,
            "y": 784.0
        },
        "sprite": {
            "is_flip": false,
            "image_path": "asset/images/Tiles/Non_Ani/Tile_D.png"
        },
        "animation": {},
        "IsAnimated": false,
        "collision": {
            "id": 0,
            "enum": "box"
        }
    },
    "Tile": {
        "grid": 768061,
        "tile_type": 0,
        "scale": {
            "x": 96.0,
            "y": 96.0
        },
        "pos": {
            "x": -592.0,
            "y": 784.0
        },
        "sprite": {
            "is_flip": false,
            "image_path": "asset/images/Tiles/Non_Ani/Tile_D.png"
        },
        "animation": {},
        "IsAnimated": false,
        "collision": {
            "id": 0,
            "enum": "box"
        }
    },
    "Tile": {
        "grid": 780861,
        "tile_type": 0,
        "scale": {
            "x": 96.0,
            "y": 96.0
        },
        "pos": {
            "x": -496.0,
            "y": 784.0
        },
        "sprite": {
            "is_flip": false,
            "image_path": "asset/images/Tiles/Non_Ani/Tile_D.png"
        },
        "animation": {},
        "IsAnimated": false,
        "collision": {
            "id": 0,
            "enum": "box"
        }
    },
    "Tile": {
        "grid": 819260,
        "tile_type": 0,
        "scale": {
            "x": 96.0,
            "y": 96.0
        },
        "pos": {
            "x": -208.0,
            "y": 688.0
        },
        "sprite": {
            "is_flip": false,
            "image_path": "asset/images/Tiles/Non_Ani/Tile_L.png"
        },
        "animation": {},
        "IsAnimated": false,
        "collision": {
            "id": 0,
            "enum": "box"
        }
    },
    "Tile": {
        "grid": 793661,
        "tile_type": 0,
        "scale": {
            "x": 96.0,
            "y": 96.0
        },
        "pos": {
            "x": -400.0,
            "y": 784.0
        },
        "sprite": {
            "is_flip": false,
            "image_path": "asset/images/Tiles/Non_Ani/Tile_D.png"
        },
        "animation": {},
        "IsAnimated": false,
        "collision": {
            "id": 0,
            "enum": "box"
        }
    },
    "Tile": {
        "grid": 819257,
        "tile_type": 0,
        "scale": {
            "x": 96.0,
            "y": 96.0
        },
        "pos": {
            "x": -208.0,
            "y": 400.0
        },
        "sprite": {
            "is_flip": false,
            "image_path": "asset/images/Tiles/Non_Ani/Tile_UL_C.png"
        },
        "animation": {},
        "IsAnimated": false,
        "collision": {
            "id": 0,
            "enum": "box"
        }
    },
    "Tile": {
        "grid": 806461,
        "tile_type": 0,
        "scale": {
            "x": 96.0,
            "y": 96.0
        },
        "pos": {
            "x": -304.0,
            "y": 784.0
        },
        "sprite": {
            "is_flip": false,
            "image_path": "asset/images/Tiles/Non_Ani/Tile_D.png"
        },
        "animation": {},
        "IsAnimated": false,
        "collision": {
            "id": 0,
            "enum": "box"
        }
    },
    "Tile": {
        "grid": 691253,
        "tile_type": 0,
        "scale": {
            "x": 96.0,
            "y": 96.0
        },
        "pos": {
            "x": -1168.0,
            "y": 16.0
        },
        "sprite": {
            "is_flip": false,
            "image_path": "asset/images/Tiles/Non_Ani/Tile_UR.png"
        },
        "animation": {},
        "IsAnimated": false,
        "collision": {
            "id": 0,
            "enum": "box"
        }
    },
    "Tile": {
        "grid": 665657,
        "tile_type": 0,
        "scale": {
            "x": 96.0,
            "y": 96.0
        },
        "pos": {
            "x": -1360.0,
            "y": 400.0
        },
        "sprite": {
            "is_flip": false,
            "image_path": "asset/images/Tiles/Non_Ani/Tile_T.png"
        },
        "animation": {},
        "IsAnimated": false,
        "collision": {
            "id": 0,
            "enum": "box"
        }
    },
    "Tile": {
        "grid": 819261,
        "tile_type": 0,
        "scale": {
            "x": 96.0,
            "y": 96.0
        },
        "pos": {
            "x": -208.0,
            "y": 784.0
        },
        "sprite": {
            "is_flip": false,
            "image_path": "asset/images/Tiles/Non_Ani/Tile_DL_C.png"
        },
        "animation": {},
        "IsAnimated": false,
        "collision": {
            "id": 0,
            "enum": "box"
        }
    },
    "Tile": {
        "grid": 793657,
        "tile_type": 0,
        "scale": {
            "x": 96.0,
            "y": 96.0
        },
        "pos": {
            "x": -400.0,
            "y": 400.0
        },
        "sprite": {
            "is_flip": false,
            "image_path": "asset/images/Tiles/Non_Ani/Tile_T.png"
        },
        "animation": {},
        "IsAnimated": false,
        "collision": {
            "id": 0,
            "enum": "box"
        }
    },
    "Tile": {
        "grid": 652860,
        "tile_type": 0,
        "scale": {
            "x": 96.0,
            "y": 96.0
        },
        "pos": {
            "x": -1456.0,
            "y": 688.0
        },
        "sprite": {
            "is_flip": false,
            "image_path": "asset/images/Tiles/Non_Ani/Tile_R.png"
        },
        "animation": {},
        "IsAnimated": false,
        "collision": {
            "id": 0,
            "enum": "box"
        }
    },
    "Tile": {
        "grid": 652859,
        "tile_type": 0,
        "scale": {
            "x": 96.0,
            "y": 96.0
        },
        "pos": {
            "x": -1456.0,
            "y": 592.0
        },
        "sprite": {
            "is_flip": false,
            "image_path": "asset/images/Tiles/Non_Ani/Tile_R.png"
        },
        "animation": {},
        "IsAnimated": false,
        "collision": {
            "id": 0,
            "enum": "box"
        }
    },
    "Tile": {
        "grid": 652858,
        "tile_type": 0,
        "scale": {
            "x": 96.0,
            "y": 96.0
        },
        "pos": {
            "x": -1456.0,
            "y": 496.0
        },
        "sprite": {
            "is_flip": false,
            "image_path": "asset/images/Tiles/Non_Ani/Tile_R.png"
        },
        "animation": {},
        "IsAnimated": false,
        "collision": {
            "id": 0,
            "enum": "box"
        }
    },
    "Tile": {
        "grid": 652857,
        "tile_type": 0,
        "scale": {
            "x": 96.0,
            "y": 96.0
        },
        "pos": {
            "x": -1456.0,
            "y": 400.0
        },
        "sprite": {
            "is_flip": false,
            "image_path": "asset/images/Tiles/Non_Ani/Tile_UR.png"
        },
        "animation": {},
        "IsAnimated": false,
        "collision": {
            "id": 0,
            "enum": "box"
        }
    },
    "Tile": {
        "grid": 768057,
        "tile_type": 0,
        "scale": {
            "x": 96.0,
            "y": 96.0
        },
        "pos": {
            "x": -592.0,
            "y": 400.0
        },
        "sprite": {
            "is_flip": false,
            "image_path": "asset/images/Tiles/Non_Ani/Tile_T.png"
        },
        "animation": {},
        "IsAnimated": false,
        "collision": {
            "id": 0,
            "enum": "box"
        }
    },
    "Tile": {
        "grid": 678457,
        "tile_type": 0,
        "scale": {
            "x": 96.0,
            "y": 96.0
        },
        "pos": {
            "x": -1264.0,
            "y": 400.0
        },
        "sprite": {
            "is_flip": false,
            "image_path": "asset/images/Tiles/Non_Ani/Tile_T.png"
        },
        "animation": {},
        "IsAnimated": false,
        "collision": {
            "id": 0,
            "enum": "box"
        }
    },
    "Tile": {
        "grid": 704053,
        "tile_type": 0,
        "scale": {
            "x": 96.0,
            "y": 96.0
        },
        "pos": {
            "x": -1072.0,
            "y": 16.0
        },
        "sprite": {
            "is_flip": false,
            "image_path": "asset/images/Tiles/Non_Ani/Tile_T.png"
        },
        "animation": {},
        "IsAnimated": false,
        "collision": {
            "id": 0,
            "enum": "box"
        }
    },
    "Tile": {
        "grid": 819259,
        "tile_type": 0,
        "scale": {
            "x": 96.0,
            "y": 96.0
        },
        "pos": {
            "x": -208.0,
            "y": 592.0
        },
        "sprite": {
            "is_flip": false,
            "image_path": "asset/images/Tiles/Non_Ani/Tile_L.png"
        },
        "animation": {},
        "IsAnimated": false,
        "collision": {
            "id": 0,
            "enum": "box"
        }
    },
    "Tile": {
        "grid": 691257,
        "tile_type": 0,
        "scale": {
            "x": 96.0,
            "y": 96.0
        },
        "pos": {
            "x": -1168.0,
            "y": 400.0
        },
        "sprite": {
            "is_flip": false,
            "image_path": "asset/images/Tiles/Non_Ani/Tile_TR.png"
        },
        "animation": {},
        "IsAnimated": false,
        "collision": {
            "id": 0,
            "enum": "box"
        }
    },
    "Tile": {
        "grid": 691256,
        "tile_type": 0,
        "scale": {
            "x": 96.0,
            "y": 96.0
        },
        "pos": {
            "x": -1168.0,
            "y": 304.0
        },
        "sprite": {
            "is_flip": false,
            "image_path": "asset/images/Tiles/Non_Ani/Tile_R.png"
        },
        "animation": {},
        "IsAnimated": false,
        "collision": {
            "id": 0,
            "enum": "box"
        }
    },
    "Tile": {
        "grid": 755255,
        "tile_type": 0,
        "scale": {
            "x": 96.0,
            "y": 96.0
        },
        "pos": {
            "x": -688.0,
            "y": 208.0
        },
        "sprite": {
            "is_flip": false,
            "image_path": "asset/images/Tiles/Non_Ani/Tile_L.png"
        },
        "animation": {},
        "IsAnimated": false,
        "collision": {
            "id": 0,
            "enum": "box"
        }
    },
    "Tile": {
        "grid": 819258,
        "tile_type": 0,
        "scale": {
            "x": 96.0,
            "y": 96.0
        },
        "pos": {
            "x": -208.0,
            "y": 496.0
        },
        "sprite": {
            "is_flip": false,
            "image_path": "asset/images/Tiles/Non_Ani/Tile_L.png"
        },
        "animation": {},
        "IsAnimated": false,
        "collision": {
            "id": 0,
            "enum": "box"
        }
    },
    "Tile": {
        "grid": 691255,
        "tile_type": 0,
        "scale": {
            "x": 96.0,
            "y": 96.0
        },
        "pos": {
            "x": -1168.0,
            "y": 208.0
        },
        "sprite": {
            "is_flip": false,
            "image_path": "asset/images/Tiles/Non_Ani/Tile_R.png"
        },
        "animation": {},
        "IsAnimated": false,
        "collision": {
            "id": 0,
            "enum": "box"
        }
    },
    "Tile": {
        "grid": 691254,
        "tile_type": 0,
        "scale": {
            "x": 96.0,
            "y": 96.0
        },
        "pos": {
            "x": -1168.0,
            "y": 112.0
        },
        "sprite": {
            "is_flip": false,
            "image_path": "asset/images/Tiles/Non_Ani/Tile_R.png"
        },
        "animation": {},
        "IsAnimated": false,
        "collision": {
            "id": 0,
            "enum": "box"
        }
    },
    "Tile": {
        "grid": 716853,
        "tile_type": 0,
        "scale": {
            "x": 96.0,
            "y": 96.0
        },
        "pos": {
            "x": -976.0,
            "y": 16.0
        },
        "sprite": {
            "is_flip": false,
            "image_path": "asset/images/Tiles/Non_Ani/Tile_T.png"
        },
        "animation": {},
        "IsAnimated": false,
        "collision": {
            "id": 0,
            "enum": "box"
        }
    },
    "Tile": {
        "grid": 755257,
        "tile_type": 0,
        "scale": {
            "x": 96.0,
            "y": 96.0
        },
        "pos": {
            "x": -688.0,
            "y": 400.0
        },
        "sprite": {
            "is_flip": false,
            "image_path": "asset/images/Tiles/Non_Ani/Tile_TL.png"
        },
        "animation": {},
        "IsAnimated": false,
        "collision": {
            "id": 0,
            "enum": "box"
        }
    },
    "Tile": {
        "grid": 729653,
        "tile_type": 0,
        "scale": {
            "x": 96.0,
            "y": 96.0
        },
        "pos": {
            "x": -880.0,
            "y": 16.0
        },
        "sprite": {
            "is_flip": false,
            "image_path": "asset/images/Tiles/Non_Ani/Tile_T.png"
        },
        "animation": {},
        "IsAnimated": false,
        "collision": {
            "id": 0,
            "enum": "box"
        }
    },
    "Tile": {
        "grid": 742453,
        "tile_type": 0,
        "scale": {
            "x": 96.0,
            "y": 96.0
        },
        "pos": {
            "x": -784.0,
            "y": 16.0
        },
        "sprite": {
            "is_flip": false,
            "image_path": "asset/images/Tiles/Non_Ani/Tile_T.png"
        },
        "animation": {},
        "IsAnimated": false,
        "collision": {
            "id": 0,
            "enum": "box"
        }
    },
    "Tile": {
        "grid": 755254,
        "tile_type": 0,
        "scale": {
            "x": 96.0,
            "y": 96.0
        },
        "pos": {
            "x": -688.0,
            "y": 112.0
        },
        "sprite": {
            "is_flip": false,
            "image_path": "asset/images/Tiles/Non_Ani/Tile_L.png"
        },
        "animation": {},
        "IsAnimated": false,
        "collision": {
            "id": 0,
            "enum": "box"
        }
    },
    "Tile": {
        "grid": 755256,
        "tile_type": 0,
        "scale": {
            "x": 96.0,
            "y": 96.0
        },
        "pos": {
            "x": -688.0,
            "y": 304.0
        },
        "sprite": {
            "is_flip": false,
            "image_path": "asset/images/Tiles/Non_Ani/Tile_L.png"
        },
        "animation": {},
        "IsAnimated": false,
        "collision": {
            "id": 0,
            "enum": "box"
        }
    },
    "Tile": {
        "grid": 755253,
        "tile_type": 0,
        "scale": {
            "x": 96.0,
            "y": 96.0
        },
        "pos": {
            "x": -688.0,
            "y": 16.0
        },
        "sprite": {
            "is_flip": false,
            "image_path": "asset/images/Tiles/Non_Ani/Tile_UL_C.png"
        },
        "animation": {},
        "IsAnimated": false,
        "collision": {
            "id": 0,
            "enum": "box"
        }
    },
    "Tile": {
        "grid": 780857,
        "tile_type": 0,
        "scale": {
            "x": 96.0,
            "y": 96.0
        },
        "pos": {
            "x": -496.0,
            "y": 400.0
        },
        "sprite": {
            "is_flip": false,
            "image_path": "asset/images/Tiles/Non_Ani/Tile_T.png"
        },
        "animation": {},
        "IsAnimated": false,
        "collision": {
            "id": 0,
            "enum": "box"
        }
    }
}